fzbackendutils/__init__.py
fzbackendutils/apps.py
fzbackendutils/signals.py
fzbackendutils/urls.py
fzbackendutils/views.py
fzbackendutils/locale/django.pot
fzbackendutils/locale/de/LC_MESSAGES/django.mo
fzbackendutils/locale/de/LC_MESSAGES/django.po
fzbackendutils/locale/de_Informal/.gitkeep
fzbackendutils/locale/de_Informal/LC_MESSAGES/django.mo
fzbackendutils/locale/de_Informal/LC_MESSAGES/django.po
fzbackendutils/static/fzbackendutils/.gitkeep
fzbackendutils/templates/fzbackendutils/settings.html
fzbackendutils-0.10.20250111.dist-info/LICENSE
fzbackendutils-0.10.20250111.dist-info/METADATA
fzbackendutils-0.10.20250111.dist-info/WHEEL
fzbackendutils-0.10.20250111.dist-info/entry_points.txt
fzbackendutils-0.10.20250111.dist-info/top_level.txt
fzbackendutils-0.10.20250111.dist-info/RECORD
