Metadata-Version: 2.2
Name: fzbackendutils
Version: 0.10.20250111
Summary: Pretix utils plugin to work together with fz-backend
Author-email: Furizon Team <webservice@furizon.net>, Luca Sorace <public.stranck@gmail.com>
Maintainer-email: Furizon Team <webservice@furizon.net>, Luca Sorace <public.stranck@gmail.com>
License: Apache
Project-URL: homepage, https://github.com/APSfurizon/pretix-fzbackend-utils
Project-URL: repository, https://github.com/APSfurizon/pretix-fzbackend-utils
Keywords: pretix
License-File: LICENSE
